spaceworld/__init__.py
spaceworld/__main__.py
spaceworld/_types.py
spaceworld/annotation_manager.py
spaceworld/base_command.py
spaceworld/base_module.py
spaceworld/cli.py
spaceworld/command.py
spaceworld/errors.py
spaceworld/module.py
spaceworld/parser_manager.py
spaceworld/spaceworld.py
spaceworld/utils.py
spaceworld/writer.py
spaceworld-3.0.0.dist-info/licenses/LICENSE
spaceworld-3.0.0.dist-info/METADATA
spaceworld-3.0.0.dist-info/WHEEL
spaceworld-3.0.0.dist-info/entry_points.txt
spaceworld-3.0.0.dist-info/top_level.txt
spaceworld-3.0.0.dist-info/RECORD
