Metadata-Version: 2.4
Name: spaceworld
Version: 3.0.0
Summary: Spaceworld is a new generation Cli framework for convenient development of your teams written in Python 3.12+ with support for asynchronous commands
Author-email: binobinos <binobinos.dev@gmail.com>
License: MIT
Project-URL: Homepage, https://github.com/Binobinos/SpaceWorld
Project-URL: Changelog, https://github.com/Binobinos/Spaceworld/blob/main/CHANGELOG.md
Project-URL: Releases, https://github.com/Binobinos/SpaceWorld/releases
Project-URL: Bug, https://github.com/Binobinos/SpaceWorld/issues
Keywords: python,shell,cli,performance,terminal,async,python3,typehints,spaceworld
Classifier: Development Status :: 4 - Beta
Classifier: Intended Audience :: Developers
Classifier: Intended Audience :: System Administrators
Classifier: Intended Audience :: Information Technology
Classifier: License :: OSI Approved :: MIT License
Classifier: Operating System :: OS Independent
Classifier: Programming Language :: Python
Classifier: Programming Language :: Python :: 3
Classifier: Programming Language :: Python :: 3 :: Only
Classifier: Programming Language :: Python :: 3.12
Classifier: Programming Language :: Python :: 3.13
Classifier: Topic :: Software Development :: Libraries
Classifier: Topic :: Software Development :: Libraries :: Application Frameworks
Classifier: Topic :: Software Development :: Libraries :: Python Modules
Classifier: Topic :: Utilities
Classifier: Topic :: System :: Shells
Classifier: Topic :: System :: Systems Administration
Classifier: Topic :: Terminals
Classifier: Topic :: Software Development :: User Interfaces
Classifier: Typing :: Typed
Requires-Python: >=3.12
License-File: LICENSE
Dynamic: license-file
